flightsong/__init__.py
flightsong/__main__.py
flightsong/main.py
flightsong/utils.py
flightsong-0.1.1.dist-info/entry_points.txt
flightsong-0.1.1.dist-info/WHEEL
flightsong-0.1.1.dist-info/METADATA
flightsong-0.1.1.dist-info/RECORD
