Metadata-Version: 2.1
Name: flightsong
Version: 0.1.1
Summary: 
Author: Jón Levy
Author-email: nonni@nonni.cc
Requires-Python: >=3.10,<4.0
Classifier: Programming Language :: Python :: 3
Classifier: Programming Language :: Python :: 3.10
Requires-Dist: requests (>=2.28.1,<3.0.0)
Requires-Dist: rich (>=12.4.4,<13.0.0)
Requires-Dist: typer[all] (>=0.4.1,<0.5.0)
